Workbook

Sheet ダッシュボード
B2: 📊 家計簿ダッシュボード
B4: 💰 年間収入 | D4: 💸 年間支出 | F4: 🏦 年間貯蓄 | H4: 📈 貯蓄率
B5: =SUM(C10:C21) | D5: =SUM(D10:D21) | F5: =B5-D5 | H5: =IF(B5=0,"--",F5/B5)
B8: 📅 月別収支サマリー | J8: 🏷️ カテゴリ別 年間支出
B9: 月 | C9: 収入 | D9: 支出 | E9: 貯蓄 | F9: 貯蓄率 | G9: 前月比支出 | H9: 評価 | J9: カテゴリ | K9: 年間合計 | L9: 構成比
B10: 1月 | C10: ='1月'!E3 | D10: ='1月'!E10 | E10: ='1月'!E3-'1月'!E10 | F10: =IF('1月'!E3=0,"",('1月'!E3-'1月'!E10)/'1月'!E3) | G10: ="--" | H10: =IF('1月'!E3=0,"",IF(('1月'!E3-'1月'!E10)/'1月'!E3>=0.2,"◎ 優秀",IF(('1月'!E3-'1月'!E10)/'1月'!E3>=0.1,"○ 良好",IF(('1月'!E3-'1月'!E10)>=0,"△ 普通","✕ 赤字")))) | J10: 住居費（家賃/ローン） | K10: ='1月'!D11+'2月'!D11+'3月'!D11+'4月'!D11+'5月'!D11+'6月'!D11+'7月'!D11+'8月'!D11+'9月'!D11+'10月'!D11+'11月'!D11+'12月'!D11 | L10: =IF(D5=0,"",K10/D5)
B11: 2月 | C11: ='2月'!E3 | D11: ='2月'!E10 | E11: ='2月'!E3-'2月'!E10 | F11: =IF('2月'!E3=0,"",('2月'!E3-'2月'!E10)/'2月'!E3) | G11: =IF(D10=0,"--",(D11-D10)/D10) | H11: =IF('2月'!E3=0,"",IF(('2月'!E3-'2月'!E10)/'2月'!E3>=0.2,"◎ 優秀",IF(('2月'!E3-'2月'!E10)/'2月'!E3>=0.1,"○ 良好",IF(('2月'!E3-'2月'!E10)>=0,"△ 普通","✕ 赤字")))) | J11: 水道光熱費 | K11: ='1月'!D12+'2月'!D12+'3月'!D12+'4月'!D12+'5月'!D12+'6月'!D12+'7月'!D12+'8月'!D12+'9月'!D12+'10月'!D12+'11月'!D12+'12月'!D12 | L11: =IF(D5=0,"",K11/D5)
B12: 3月 | C12: ='3月'!E3 | D12: ='3月'!E10 | E12: ='3月'!E3-'3月'!E10 | F12: =IF('3月'!E3=0,"",('3月'!E3-'3月'!E10)/'3月'!E3) | G12: =IF(D11=0,"--",(D12-D11)/D11) | H12: =IF('3月'!E3=0,"",IF(('3月'!E3-'3月'!E10)/'3月'!E3>=0.2,"◎ 優秀",IF(('3月'!E3-'3月'!E10)/'3月'!E3>=0.1,"○ 良好",IF(('3月'!E3-'3月'!E10)>=0,"△ 普通","✕ 赤字")))) | J12: 食費 | K12: ='1月'!D13+'2月'!D13+'3月'!D13+'4月'!D13+'5月'!D13+'6月'!D13+'7月'!D13+'8月'!D13+'9月'!D13+'10月'!D13+'11月'!D13+'12月'!D13 | L12: =IF(D5=0,"",K12/D5)
B13: 4月 | C13: ='4月'!E3 | D13: ='4月'!E10 | E13: ='4月'!E3-'4月'!E10 | F13: =IF('4月'!E3=0,"",('4月'!E3-'4月'!E10)/'4月'!E3) | G13: =IF(D12=0,"--",(D13-D12)/D12) | H13: =IF('4月'!E3=0,"",IF(('4月'!E3-'4月'!E10)/'4月'!E3>=0.2,"◎ 優秀",IF(('4月'!E3-'4月'!E10)/'4月'!E3>=0.1,"○ 良好",IF(('4月'!E3-'4月'!E10)>=0,"△ 普通","✕ 赤字")))) | J13: 日用品 | K13: ='1月'!D14+'2月'!D14+'3月'!D14+'4月'!D14+'5月'!D14+'6月'!D14+'7月'!D14+'8月'!D14+'9月'!D14+'10月'!D14+'11月'!D14+'12月'!D14 | L13: =IF(D5=0,"",K13/D5)
B14: 5月 | C14: ='5月'!E3 | D14: ='5月'!E10 | E14: ='5月'!E3-'5月'!E10 | F14: =IF('5月'!E3=0,"",('5月'!E3-'5月'!E10)/'5月'!E3) | G14: =IF(D13=0,"--",(D14-D13)/D13) | H14: =IF('5月'!E3=0,"",IF(('5月'!E3-'5月'!E10)/'5月'!E3>=0.2,"◎ 優秀",IF(('5月'!E3-'5月'!E10)/'5月'!E3>=0.1,"○ 良好",IF(('5月'!E3-'5月'!E10)>=0,"△ 普通","✕ 赤字")))) | J14: 交通費 | K14: ='1月'!D15+'2月'!D15+'3月'!D15+'4月'!D15+'5月'!D15+'6月'!D15+'7月'!D15+'8月'!D15+'9月'!D15+'10月'!D15+'11月'!D15+'12月'!D15 | L14: =IF(D5=0,"",K14/D5)
B15: 6月 | C15: ='6月'!E3 | D15: ='6月'!E10 | E15: ='6月'!E3-'6月'!E10 | F15: =IF('6月'!E3=0,"",('6月'!E3-'6月'!E10)/'6月'!E3) | G15: =IF(D14=0,"--",(D15-D14)/D14) | H15: =IF('6月'!E3=0,"",IF(('6月'!E3-'6月'!E10)/'6月'!E3>=0.2,"◎ 優秀",IF(('6月'!E3-'6月'!E10)/'6月'!E3>=0.1,"○ 良好",IF(('6月'!E3-'6月'!E10)>=0,"△ 普通","✕ 赤字")))) | J15: 通信費 | K15: ='1月'!D16+'2月'!D16+'3月'!D16+'4月'!D16+'5月'!D16+'6月'!D16+'7月'!D16+'8月'!D16+'9月'!D16+'10月'!D16+'11月'!D16+'12月'!D16 | L15: =IF(D5=0,"",K15/D5)
B16: 7月 | C16: ='7月'!E3 | D16: ='7月'!E10 | E16: ='7月'!E3-'7月'!E10 | F16: =IF('7月'!E3=0,"",('7月'!E3-'7月'!E10)/'7月'!E3) | G16: =IF(D15=0,"--",(D16-D15)/D15) | H16: =IF('7月'!E3=0,"",IF(('7月'!E3-'7月'!E10)/'7月'!E3>=0.2,"◎ 優秀",IF(('7月'!E3-'7月'!E10)/'7月'!E3>=0.1,"○ 良好",IF(('7月'!E3-'7月'!E10)>=0,"△ 普通","✕ 赤字")))) | J16: 保険料 | K16: ='1月'!D17+'2月'!D17+'3月'!D17+'4月'!D17+'5月'!D17+'6月'!D17+'7月'!D17+'8月'!D17+'9月'!D17+'10月'!D17+'11月'!D17+'12月'!D17 | L16: =IF(D5=0,"",K16/D5)
B17: 8月 | C17: ='8月'!E3 | D17: ='8月'!E10 | E17: ='8月'!E3-'8月'!E10 | F17: =IF('8月'!E3=0,"",('8月'!E3-'8月'!E10)/'8月'!E3) | G17: =IF(D16=0,"--",(D17-D16)/D16) | H17: =IF('8月'!E3=0,"",IF(('8月'!E3-'8月'!E10)/'8月'!E3>=0.2,"◎ 優秀",IF(('8月'!E3-'8月'!E10)/'8月'!E3>=0.1,"○ 良好",IF(('8月'!E3-'8月'!E10)>=0,"△ 普通","✕ 赤字")))) | J17: 医療費 | K17: ='1月'!D18+'2月'!D18+'3月'!D18+'4月'!D18+'5月'!D18+'6月'!D18+'7月'!D18+'8月'!D18+'9月'!D18+'10月'!D18+'11月'!D18+'12月'!D18 | L17: =IF(D5=0,"",K17/D5)
B18: 9月 | C18: ='9月'!E3 | D18: ='9月'!E10 | E18: ='9月'!E3-'9月'!E10 | F18: =IF('9月'!E3=0,"",('9月'!E3-'9月'!E10)/'9月'!E3) | G18: =IF(D17=0,"--",(D18-D17)/D17) | H18: =IF('9月'!E3=0,"",IF(('9月'!E3-'9月'!E10)/'9月'!E3>=0.2,"◎ 優秀",IF(('9月'!E3-'9月'!E10)/'9月'!E3>=0.1,"○ 良好",IF(('9月'!E3-'9月'!E10)>=0,"△ 普通","✕ 赤字")))) | J18: 教育費 | K18: ='1月'!D19+'2月'!D19+'3月'!D19+'4月'!D19+'5月'!D19+'6月'!D19+'7月'!D19+'8月'!D19+'9月'!D19+'10月'!D19+'11月'!D19+'12月'!D19 | L18: =IF(D5=0,"",K18/D5)
B19: 10月 | C19: ='10月'!E3 | D19: ='10月'!E10 | E19: ='10月'!E3-'10月'!E10 | F19: =IF('10月'!E3=0,"",('10月'!E3-'10月'!E10)/'10月'!E3) | G19: =IF(D18=0,"--",(D19-D18)/D18) | H19: =IF('10月'!E3=0,"",IF(('10月'!E3-'10月'!E10)/'10月'!E3>=0.2,"◎ 優秀",IF(('10月'!E3-'10月'!E10)/'10月'!E3>=0.1,"○ 良好",IF(('10月'!E3-'10月'!E10)>=0,"△ 普通","✕ 赤字")))) | J19: 娯楽費 | K19: ='1月'!D20+'2月'!D20+'3月'!D20+'4月'!D20+'5月'!D20+'6月'!D20+'7月'!D20+'8月'!D20+'9月'!D20+'10月'!D20+'11月'!D20+'12月'!D20 | L19: =IF(D5=0,"",K19/D5)
B20: 11月 | C20: ='11月'!E3 | D20: ='11月'!E10 | E20: ='11月'!E3-'11月'!E10 | F20: =IF('11月'!E3=0,"",('11月'!E3-'11月'!E10)/'11月'!E3) | G20: =IF(D19=0,"--",(D20-D19)/D19) | H20: =IF('11月'!E3=0,"",IF(('11月'!E3-'11月'!E10)/'11月'!E3>=0.2,"◎ 優秀",IF(('11月'!E3-'11月'!E10)/'11月'!E3>=0.1,"○ 良好",IF(('11月'!E3-'11月'!E10)>=0,"△ 普通","✕ 赤字")))) | J20: 衣服費 | K20: ='1月'!D21+'2月'!D21+'3月'!D21+'4月'!D21+'5月'!D21+'6月'!D21+'7月'!D21+'8月'!D21+'9月'!D21+'10月'!D21+'11月'!D21+'12月'!D21 | L20: =IF(D5=0,"",K20/D5)
B21: 12月 | C21: ='12月'!E3 | D21: ='12月'!E10 | E21: ='12月'!E3-'12月'!E10 | F21: =IF('12月'!E3=0,"",('12月'!E3-'12月'!E10)/'12月'!E3) | G21: =IF(D20=0,"--",(D21-D20)/D20) | H21: =IF('12月'!E3=0,"",IF(('12月'!E3-'12月'!E10)/'12月'!E3>=0.2,"◎ 優秀",IF(('12月'!E3-'12月'!E10)/'12月'!E3>=0.1,"○ 良好",IF(('12月'!E3-'12月'!E10)>=0,"△ 普通","✕ 赤字")))) | J21: 美容費 | K21: ='1月'!D22+'2月'!D22+'3月'!D22+'4月'!D22+'5月'!D22+'6月'!D22+'7月'!D22+'8月'!D22+'9月'!D22+'10月'!D22+'11月'!D22+'12月'!D22 | L21: =IF(D5=0,"",K21/D5)
J22: 交際費 | K22: ='1月'!D23+'2月'!D23+'3月'!D23+'4月'!D23+'5月'!D23+'6月'!D23+'7月'!D23+'8月'!D23+'9月'!D23+'10月'!D23+'11月'!D23+'12月'!D23 | L22: =IF(D5=0,"",K22/D5)
B23: 📊 月別 収入 vs 支出 推移 | J23: その他 | K23: ='1月'!D24+'2月'!D24+'3月'!D24+'4月'!D24+'5月'!D24+'6月'!D24+'7月'!D24+'8月'!D24+'9月'!D24+'10月'!D24+'11月'!D24+'12月'!D24 | L23: =IF(D5=0,"",K23/D5)
B41: 💰 月別貯蓄額の推移

Sheet 1月
B1: 📋 1月 家計簿
B3: 【収入】 | E3: =SUM(D4:D7)
B4: 給与 | C4: 0 | D4: 300000
B5: 副業 | C5: 0 | D5: 50000
B6: 投資収入 | C6: 0 | D6: 5000
B7: その他収入 | C7: 0 | D7: 0
B10: 【支出】 | E10: =SUM(D11:D24)
B11: 住居費（家賃/ローン） | C11: 0 | D11: 80000
B12: 水道光熱費 | C12: 0 | D12: 15000
B13: 食費 | C13: 0 | D13: 45000
B14: 日用品 | C14: 0 | D14: 8000
B15: 交通費 | C15: 0 | D15: 12000
B16: 通信費 | C16: 0 | D16: 10000
B17: 保険料 | C17: 0 | D17: 15000
B18: 医療費 | C18: 0 | D18: 3000
B19: 教育費 | C19: 0 | D19: 0
B20: 娯楽費 | C20: 0 | D20: 15000
B21: 衣服費 | C21: 0 | D21: 5000
B22: 美容費 | C22: 0 | D22: 3000
... B24: その他 | C24: 0 | D24: 5000
B27: 【収支バランス】
B28: 収入合計 | D28: =E3
B29: 支出合計 | D29: =E10
B30: 差額（貯蓄） | D30: =D28-D29
B33: 【日別支出記録】
B34: 日付 | C34: カテゴリ | D34: 金額 | E34: 支払方法 | F34: メモ

Sheet 2月
B1: 📋 2月 家計簿
B3: 【収入】 | E3: =SUM(D4:D7)
B4: 給与 | C4: 0 | D4: 300000
B5: 副業 | C5: 0 | D5: 45000
B6: 投資収入 | C6: 0 | D6: 5000
B7: その他収入 | C7: 0 | D7: 10000
B10: 【支出】 | E10: =SUM(D11:D24)
B11: 住居費（家賃/ローン） | C11: 0 | D11: 80000
B12: 水道光熱費 | C12: 0 | D12: 13000
B13: 食費 | C13: 0 | D13: 42000
B14: 日用品 | C14: 0 | D14: 7000
B15: 交通費 | C15: 0 | D15: 11000
B16: 通信費 | C16: 0 | D16: 10000
B17: 保険料 | C17: 0 | D17: 15000
B18: 医療費 | C18: 0 | D18: 5000
B19: 教育費 | C19: 0 | D19: 0
B20: 娯楽費 | C20: 0 | D20: 12000
B21: 衣服費 | C21: 0 | D21: 3000
B22: 美容費 | C22: 0 | D22: 4000
... B24: その他 | C24: 0 | D24: 4000
B27: 【収支バランス】
B28: 収入合計 | D28: =E3
B29: 支出合計 | D29: =E10
B30: 差額（貯蓄） | D30: =D28-D29
B33: 【日別支出記録】
B34: 日付 | C34: カテゴリ | D34: 金額 | E34: 支払方法 | F34: メモ

Sheet 3月
B1: 📋 3月 家計簿
B3: 【収入】 | E3: =SUM(D4:D7)
B4: 給与 | C4: 0 | D4: 300000
B5: 副業 | C5: 0 | D5: 60000
B6: 投資収入 | C6: 0 | D6: 8000
B7: その他収入 | C7: 0 | D7: 0
B10: 【支出】 | E10: =SUM(D11:D24)
B11: 住居費（家賃/ローン） | C11: 0 | D11: 80000
B12: 水道光熱費 | C12: 0 | D12: 12000
B13: 食費 | C13: 0 | D13: 48000
B14: 日用品 | C14: 0 | D14: 9000
B15: 交通費 | C15: 0 | D15: 13000
B16: 通信費 | C16: 0 | D16: 10000
B17: 保険料 | C17: 0 | D17: 15000
B18: 医療費 | C18: 0 | D18: 0
B19: 教育費 | C19: 0 | D19: 5000
B20: 娯楽費 | C20: 0 | D20: 20000
B21: 衣服費 | C21: 0 | D21: 8000
B22: 美容費 | C22: 0 | D22: 3000
... B24: その他 | C24: 0 | D24: 6000
B27: 【収支バランス】
B28: 収入合計 | D28: =E3
B29: 支出合計 | D29: =E10
B30: 差額（貯蓄） | D30: =D28-D29
B33: 【日別支出記録】
B34: 日付 | C34: カテゴリ | D34: 金額 | E34: 支払方法 | F34: メモ

Sheet 4月
B1: 📋 4月 家計簿
B3: 【収入】 | E3: =SUM(D4:D7)
B4: 給与 | C4: 0 | D4: 0
B5: 副業 | C5: 0 | D5: 0
B6: 投資収入 | C6: 0 | D6: 0
B7: その他収入 | C7: 0 | D7: 0
B10: 【支出】 | E10: =SUM(D11:D24)
B11: 住居費（家賃/ローン） | C11: 0 | D11: 0
B12: 水道光熱費 | C12: 0 | D12: 0
B13: 食費 | C13: 0 | D13: 0
B14: 日用品 | C14: 0 | D14: 0
B15: 交通費 | C15: 0 | D15: 0
B16: 通信費 | C16: 0 | D16: 0
B17: 保険料 | C17: 0 | D17: 0
B18: 医療費 | C18: 0 | D18: 0
B19: 教育費 | C19: 0 | D19: 0
B20: 娯楽費 | C20: 0 | D20: 0
B21: 衣服費 | C21: 0 | D21: 0
B22: 美容費 | C22: 0 | D22: 0
... B24: その他 | C24: 0 | D24: 0
B27: 【収支バランス】
B28: 収入合計 | D28: =E3
B29: 支出合計 | D29: =E10
B30: 差額（貯蓄） | D30: =D28-D29
B33: 【日別支出記録】
B34: 日付 | C34: カテゴリ | D34: 金額 | E34: 支払方法 | F34: メモ

Sheet 5月
B1: 📋 5月 家計簿
B3: 【収入】 | E3: =SUM(D4:D7)
B4: 給与 | C4: 0 | D4: 0
B5: 副業 | C5: 0 | D5: 0
B6: 投資収入 | C6: 0 | D6: 0
B7: その他収入 | C7: 0 | D7: 0
B10: 【支出】 | E10: =SUM(D11:D24)
B11: 住居費（家賃/ローン） | C11: 0 | D11: 0
B12: 水道光熱費 | C12: 0 | D12: 0
B13: 食費 | C13: 0 | D13: 0
B14: 日用品 | C14: 0 | D14: 0
B15: 交通費 | C15: 0 | D15: 0
B16: 通信費 | C16: 0 | D16: 0
B17: 保険料 | C17: 0 | D17: 0
B18: 医療費 | C18: 0 | D18: 0
B19: 教育費 | C19: 0 | D19: 0
B20: 娯楽費 | C20: 0 | D20: 0
B21: 衣服費 | C21: 0 | D21: 0
B22: 美容費 | C22: 0 | D22: 0
... B24: その他 | C24: 0 | D24: 0
B27: 【収支バランス】
B28: 収入合計 | D28: =E3
B29: 支出合計 | D29: =E10
B30: 差額（貯蓄） | D30: =D28-D29
B33: 【日別支出記録】
B34: 日付 | C34: カテゴリ | D34: 金額 | E34: 支払方法 | F34: メモ

Sheet 6月
B1: 📋 6月 家計簿
B3: 【収入】 | E3: =SUM(D4:D7)
B4: 給与 | C4: 0 | D4: 0
B5: 副業 | C5: 0 | D5: 0
B6: 投資収入 | C6: 0 | D6: 0
B7: その他収入 | C7: 0 | D7: 0
B10: 【支出】 | E10: =SUM(D11:D24)
B11: 住居費（家賃/ローン） | C11: 0 | D11: 0
B12: 水道光熱費 | C12: 0 | D12: 0
B13: 食費 | C13: 0 | D13: 0
B14: 日用品 | C14: 0 | D14: 0
B15: 交通費 | C15: 0 | D15: 0
B16: 通信費 | C16: 0 | D16: 0
B17: 保険料 | C17: 0 | D17: 0
B18: 医療費 | C18: 0 | D18: 0
B19: 教育費 | C19: 0 | D19: 0
B20: 娯楽費 | C20: 0 | D20: 0
B21: 衣服費 | C21: 0 | D21: 0
B22: 美容費 | C22: 0 | D22: 0
... B24: その他 | C24: 0 | D24: 0
B27: 【収支バランス】
B28: 収入合計 | D28: =E3
B29: 支出合計 | D29: =E10
B30: 差額（貯蓄） | D30: =D28-D29
B33: 【日別支出記録】
B34: 日付 | C34: カテゴリ | D34: 金額 | E34: 支払方法 | F34: メモ

Sheet 7月
B1: 📋 7月 家計簿
B3: 【収入】 | E3: =SUM(D4:D7)
B4: 給与 | C4: 0 | D4: 0
B5: 副業 | C5: 0 | D5: 0
B6: 投資収入 | C6: 0 | D6: 0
B7: その他収入 | C7: 0 | D7: 0
B10: 【支出】 | E10: =SUM(D11:D24)
B11: 住居費（家賃/ローン） | C11: 0 | D11: 0
B12: 水道光熱費 | C12: 0 | D12: 0
B13: 食費 | C13: 0 | D13: 0
B14: 日用品 | C14: 0 | D14: 0
B15: 交通費 | C15: 0 | D15: 0
B16: 通信費 | C16: 0 | D16: 0
B17: 保険料 | C17: 0 | D17: 0
B18: 医療費 | C18: 0 | D18: 0
B19: 教育費 | C19: 0 | D19: 0
B20: 娯楽費 | C20: 0 | D20: 0
B21: 衣服費 | C21: 0 | D21: 0
B22: 美容費 | C22: 0 | D22: 0
... B24: その他 | C24: 0 | D24: 0
B27: 【収支バランス】
B28: 収入合計 | D28: =E3
B29: 支出合計 | D29: =E10
B30: 差額（貯蓄） | D30: =D28-D29
B33: 【日別支出記録】
B34: 日付 | C34: カテゴリ | D34: 金額 | E34: 支払方法 | F34: メモ

Sheet 8月
B1: 📋 8月 家計簿
B3: 【収入】 | E3: =SUM(D4:D7)
B4: 給与 | C4: 0 | D4: 0
B5: 副業 | C5: 0 | D5: 0
B6: 投資収入 | C6: 0 | D6: 0
B7: その他収入 | C7: 0 | D7: 0
B10: 【支出】 | E10: =SUM(D11:D24)
B11: 住居費（家賃/ローン） | C11: 0 | D11: 0
B12: 水道光熱費 | C12: 0 | D12: 0
B13: 食費 | C13: 0 | D13: 0
B14: 日用品 | C14: 0 | D14: 0
B15: 交通費 | C15: 0 | D15: 0
B16: 通信費 | C16: 0 | D16: 0
B17: 保険料 | C17: 0 | D17: 0
B18: 医療費 | C18: 0 | D18: 0
B19: 教育費 | C19: 0 | D19: 0
B20: 娯楽費 | C20: 0 | D20: 0
B21: 衣服費 | C21: 0 | D21: 0
B22: 美容費 | C22: 0 | D22: 0
... B24: その他 | C24: 0 | D24: 0
B27: 【収支バランス】
B28: 収入合計 | D28: =E3
B29: 支出合計 | D29: =E10
B30: 差額（貯蓄） | D30: =D28-D29
B33: 【日別支出記録】
B34: 日付 | C34: カテゴリ | D34: 金額 | E34: 支払方法 | F34: メモ

Sheet 9月
B1: 📋 9月 家計簿
B3: 【収入】 | E3: =SUM(D4:D7)
B4: 給与 | C4: 0 | D4: 0
B5: 副業 | C5: 0 | D5: 0
B6: 投資収入 | C6: 0 | D6: 0
B7: その他収入 | C7: 0 | D7: 0
B10: 【支出】 | E10: =SUM(D11:D24)
B11: 住居費（家賃/ローン） | C11: 0 | D11: 0
B12: 水道光熱費 | C12: 0 | D12: 0
B13: 食費 | C13: 0 | D13: 0
B14: 日用品 | C14: 0 | D14: 0
B15: 交通費 | C15: 0 | D15: 0
B16: 通信費 | C16: 0 | D16: 0
B17: 保険料 | C17: 0 | D17: 0
B18: 医療費 | C18: 0 | D18: 0
B19: 教育費 | C19: 0 | D19: 0
B20: 娯楽費 | C20: 0 | D20: 0
B21: 衣服費 | C21: 0 | D21: 0
B22: 美容費 | C22: 0 | D22: 0
... B24: その他 | C24: 0 | D24: 0
B27: 【収支バランス】
B28: 収入合計 | D28: =E3
B29: 支出合計 | D29: =E10
B30: 差額（貯蓄） | D30: =D28-D29
B33: 【日別支出記録】
B34: 日付 | C34: カテゴリ | D34: 金額 | E34: 支払方法 | F34: メモ

Sheet 10月
B1: 📋 10月 家計簿
B3: 【収入】 | E3: =SUM(D4:D7)
B4: 給与 | C4: 0 | D4: 0
B5: 副業 | C5: 0 | D5: 0
B6: 投資収入 | C6: 0 | D6: 0
B7: その他収入 | C7: 0 | D7: 0
B10: 【支出】 | E10: =SUM(D11:D24)
B11: 住居費（家賃/ローン） | C11: 0 | D11: 0
B12: 水道光熱費 | C12: 0 | D12: 0
B13: 食費 | C13: 0 | D13: 0
B14: 日用品 | C14: 0 | D14: 0
B15: 交通費 | C15: 0 | D15: 0
B16: 通信費 | C16: 0 | D16: 0
B17: 保険料 | C17: 0 | D17: 0
B18: 医療費 | C18: 0 | D18: 0
B19: 教育費 | C19: 0 | D19: 0
B20: 娯楽費 | C20: 0 | D20: 0
B21: 衣服費 | C21: 0 | D21: 0
B22: 美容費 | C22: 0 | D22: 0
... B24: その他 | C24: 0 | D24: 0
B27: 【収支バランス】
B28: 収入合計 | D28: =E3
B29: 支出合計 | D29: =E10
B30: 差額（貯蓄） | D30: =D28-D29
B33: 【日別支出記録】
B34: 日付 | C34: カテゴリ | D34: 金額 | E34: 支払方法 | F34: メモ

Sheet 11月
B1: 📋 11月 家計簿
B3: 【収入】 | E3: =SUM(D4:D7)
B4: 給与 | C4: 0 | D4: 0
B5: 副業 | C5: 0 | D5: 0
B6: 投資収入 | C6: 0 | D6: 0
B7: その他収入 | C7: 0 | D7: 0
B10: 【支出】 | E10: =SUM(D11:D24)
B11: 住居費（家賃/ローン） | C11: 0 | D11: 0
B12: 水道光熱費 | C12: 0 | D12: 0
B13: 食費 | C13: 0 | D13: 0
B14: 日用品 | C14: 0 | D14: 0
B15: 交通費 | C15: 0 | D15: 0
B16: 通信費 | C16: 0 | D16: 0
B17: 保険料 | C17: 0 | D17: 0
B18: 医療費 | C18: 0 | D18: 0
B19: 教育費 | C19: 0 | D19: 0
B20: 娯楽費 | C20: 0 | D20: 0
B21: 衣服費 | C21: 0 | D21: 0
B22: 美容費 | C22: 0 | D22: 0
... B24: その他 | C24: 0 | D24: 0
B27: 【収支バランス】
B28: 収入合計 | D28: =E3
B29: 支出合計 | D29: =E10
B30: 差額（貯蓄） | D30: =D28-D29
B33: 【日別支出記録】
B34: 日付 | C34: カテゴリ | D34: 金額 | E34: 支払方法 | F34: メモ

Sheet 12月
B1: 📋 12月 家計簿
B3: 【収入】 | E3: =SUM(D4:D7)
B4: 給与 | C4: 0 | D4: 0
B5: 副業 | C5: 0 | D5: 0
B6: 投資収入 | C6: 0 | D6: 0
B7: その他収入 | C7: 0 | D7: 0
B10: 【支出】 | E10: =SUM(D11:D24)
B11: 住居費（家賃/ローン） | C11: 0 | D11: 0
B12: 水道光熱費 | C12: 0 | D12: 0
B13: 食費 | C13: 0 | D13: 0
B14: 日用品 | C14: 0 | D14: 0
B15: 交通費 | C15: 0 | D15: 0
B16: 通信費 | C16: 0 | D16: 0
B17: 保険料 | C17: 0 | D17: 0
B18: 医療費 | C18: 0 | D18: 0
B19: 教育費 | C19: 0 | D19: 0
B20: 娯楽費 | C20: 0 | D20: 0
B21: 衣服費 | C21: 0 | D21: 0
B22: 美容費 | C22: 0 | D22: 0
... B24: その他 | C24: 0 | D24: 0
B27: 【収支バランス】
B28: 収入合計 | D28: =E3
B29: 支出合計 | D29: =E10
B30: 差額（貯蓄） | D30: =D28-D29
B33: 【日別支出記録】
B34: 日付 | C34: カテゴリ | D34: 金額 | E34: 支払方法 | F34: メモ

Sheet 固定費・サブスク管理
B1: 📌 固定費・サブスクリプション管理
B3: 項目名 | C3: 月額 | D3: 支払日 | E3: 支払方法 | F3: カテゴリ | G3: 次回支払日 | H3: ステータス
B4: 家賃 | C4: 80000 | D4: 25 | E4: 口座振替 | F4: 住居費
B5: 電気代 | C5: 8000 | D5: 15 | E5: 口座振替 | F5: 水道光熱費
B6: ガス代 | C6: 5000 | D6: 15 | E6: 口座振替 | F6: 水道光熱費
B7: 水道代 | C7: 4000 | D7: 15 | E7: 口座振替 | F7: 水道光熱費
B8: 携帯電話 | C8: 5000 | D8: 10 | E8: クレジットカード | F8: 通信費
B9: インターネット | C9: 5000 | D9: 20 | E9: クレジットカード | F9: 通信費
B10: Netflix | C10: 1490 | D10: 1 | E10: クレジットカード | F10: 娯楽費
B11: Spotify | C11: 980 | D11: 1 | E11: クレジットカード | F11: 娯楽費
B12: 生命保険 | C12: 10000 | D12: 27 | E12: 口座振替 | F12: 保険料
C13: 0
C14: 0
C15: 0
B17: 月額合計 | C17: =SUM(C4:C15)

Sheet 貯蓄目標
B1: 🎯 貯蓄目標トラッカー
B3: 目標名 | C3: 目標金額 | D3: 現在の貯蓄 | E3: 残り | F3: 達成率 | G3: 期限
B4: 緊急予備費 | C4: 1000000 | D4: 300000 | E4: =C4-D4 | F4: =D4/C4
B5: 旅行資金 | C5: 500000 | D5: 150000 | E5: =C5-D5 | F5: =D5/C5
B6: 車購入 | C6: 2000000 | D6: 500000 | E6: =C6-D6 | F6: =D6/C6
B7: 教育資金 | C7: 3000000 | D7: 800000 | E7: =C7-D7 | F7: =D7/C7
B8: 老後資金 | C8: 10000000 | D8: 1000000 | E8: =C8-D8 | F8: =D8/C8

Sheet 使い方ガイド
B1: 📖 家計簿の使い方ガイド
B3: 【はじめに】
B4: この家計簿テンプレートは、毎月の収入と支出を管理し、
B5: 年間の貯蓄目標を達成するためのツールです。
B7: 【基本的な使い方】
B8: 1. 各月のシートに毎日の収入と支出を記録します
B9: 2. カテゴリごとの予算を設定します（予算列に入力）
B10: 3. 実績を入力すると、自動的に合計が計算されます
B11: 4. ダッシュボードで年間のサマリーを確認できます
B13: 【シートの説明】
B14: • ダッシュボード：年間の収支サマリーとグラフ
B15: • 1月〜12月：各月の収支管理と日別支出記録
... B33: • 定期的にバックアップを取ることをおすすめします
